coh_piggs_extractor/__init__.py
coh_piggs_extractor/coh_piggs_extractor.py
coh_pigs_extractor/__init__.py
coh_pigs_extractor/coh_piggs_extractor.py
coh_piggs_extractor-1.0.1.dist-info/LICENSE
coh_piggs_extractor-1.0.1.dist-info/METADATA
coh_piggs_extractor-1.0.1.dist-info/WHEEL
coh_piggs_extractor-1.0.1.dist-info/top_level.txt
coh_piggs_extractor-1.0.1.dist-info/RECORD
