Metadata-Version: 2.1
Name: coh-piggs-extractor
Version: 1.0.1
Summary: A simple module to extract files from the COH piggs file format
Home-page: https://github.com/codersparks-coh-tools/coh-piggs-extractor/
Author: codersparks
Author-email: codersparks@users.noreply.github.com
License: UNKNOWN
Project-URL: Bug Tracker, https://github.com/codersparks-coh-tools/coh-piggs-extractor/issues
Platform: UNKNOWN
Classifier: Programming Language :: Python :: 3
Classifier: License :: OSI Approved :: MIT License
Classifier: Operating System :: OS Independent
Requires-Python: >=3.8
